{"port": "sanctipetri", "month": 2, "2020-02-01": {"first_tide": {"meters": 1.026, "time": "01:18", "coefficient": 0.44}, "second_tide": {"meters": 2.362, "time": "07:42", "coefficient": 0.44}, "third_tide": {"meters": 1.023, "time": "13:47", "coefficient": 0.42}, "fourth_tide": {"meters": 2.22, "time": "20:11", "coefficient": 0.42}}, "2020-02-02": {"first_tide": {"meters": 1.144, "time": "02:12", "coefficient": 0.4}, "second_tide": {"meters": 2.252, "time": "08:39", "coefficient": 0.4}, "third_tide": {"meters": 1.138, "time": "14:47", "coefficient": 0.4}, "fourth_tide": {"meters": 2.168, "time": "21:20", "coefficient": 0.4}}, "2020-02-03": {"first_tide": {"meters": 1.217, "time": "03:24", "coefficient": 0.4}, "second_tide": {"meters": 2.213, "time": "09:55", "coefficient": 0.4}, "third_tide": {"meters": 1.196, "time": "16:03", "coefficient": 0.43}, "fourth_tide": {"meters": 2.216, "time": "22:41", "coefficient": 0.43}}, "2020-02-04": {"first_tide": {"meters": 1.194, "time": "04:45", "coefficient": 0.46}, "second_tide": {"meters": 2.276, "time": "11:17", "coefficient": 0.46}, "third_tide": {"meters": 1.15, "time": "17:18", "coefficient": 0.51}, "fourth_tide": {"meters": 2.356, "time": "23:52", "coefficient": 0.51}}, "2020-02-05": {"first_tide": {"meters": 1.063, "time": "05:57", "coefficient": 0.56}, "second_tide": {"meters": 2.412, "time": "12:25", "coefficient": 0.63}, "third_tide": {"meters": 1.006, "time": "18:22", "coefficient": 0.63}}, "2020-02-06": {"first_tide": {"meters": 2.535, "time": "00:49", "coefficient": 0.69}, "second_tide": {"meters": 0.854, "time": "06:56", "coefficient": 0.69}, "third_tide": {"meters": 2.577, "time": "13:20", "coefficient": 0.75}, "fourth_tide": {"meters": 0.809, "time": "19:16", "coefficient": 0.75}}, "2020-02-07": {"first_tide": {"meters": 2.727, "time": "01:39", "coefficient": 0.82}, "second_tide": {"meters": 0.62, "time": "07:48", "coefficient": 0.82}, "third_tide": {"meters": 2.752, "time": "14:09", "coefficient": 0.88}, "fourth_tide": {"meters": 0.608, "time": "20:05", "coefficient": 0.88}}, "2020-02-08": {"first_tide": {"meters": 2.92, "time": "02:25", "coefficient": 0.93}, "second_tide": {"meters": 0.408, "time": "08:35", "coefficient": 0.93}, "third_tide": {"meters": 2.923, "time": "14:54", "coefficient": 0.98}, "fourth_tide": {"meters": 0.444, "time": "20:50", "coefficient": 0.98}}, "2020-02-09": {"first_tide": {"meters": 3.104, "time": "03:10", "coefficient": 1.01}, "second_tide": {"meters": 0.249, "time": "09:20", "coefficient": 1.01}, "third_tide": {"meters": 3.066, "time": "15:38", "coefficient": 1.04}, "fourth_tide": {"meters": 0.331, "time": "21:35", "coefficient": 1.04}}, "2020-02-10": {"first_tide": {"meters": 3.251, "time": "03:54", "coefficient": 1.05}, "second_tide": {"meters": 0.158, "time": "10:05", "coefficient": 1.05}, "third_tide": {"meters": 3.153, "time": "16:22", "coefficient": 1.05}, "fourth_tide": {"meters": 0.276, "time": "22:18", "coefficient": 1.05}}, "2020-02-11": {"first_tide": {"meters": 3.33, "time": "04:39", "coefficient": 1.04}, "second_tide": {"meters": 0.145, "time": "10:48", "coefficient": 1.04}, "third_tide": {"meters": 3.164, "time": "17:05", "coefficient": 1.01}, "fourth_tide": {"meters": 0.281, "time": "23:00", "coefficient": 1.01}}, "2020-02-12": {"first_tide": {"meters": 3.316, "time": "05:23", "coefficient": 0.97}, "second_tide": {"meters": 0.21, "time": "11:30", "coefficient": 0.97}, "third_tide": {"meters": 3.089, "time": "17:48", "coefficient": 0.92}, "fourth_tide": {"meters": 0.347, "time": "23:43", "coefficient": 0.92}}, "2020-02-13": {"first_tide": {"meters": 3.201, "time": "06:09", "coefficient": 0.86}, "second_tide": {"meters": 0.345, "time": "12:13", "coefficient": 0.79}, "third_tide": {"meters": 2.939, "time": "18:34", "coefficient": 0.79}}, "2020-02-14": {"first_tide": {"meters": 0.473, "time": "00:27", "coefficient": 0.72}, "second_tide": {"meters": 3.001, "time": "06:57", "coefficient": 0.72}, "third_tide": {"meters": 0.535, "time": "12:58", "coefficient": 0.65}, "fourth_tide": {"meters": 2.739, "time": "19:23", "coefficient": 0.65}}, "2020-02-15": {"first_tide": {"meters": 0.65, "time": "01:15", "coefficient": 0.58}, "second_tide": {"meters": 2.756, "time": "07:51", "coefficient": 0.58}, "third_tide": {"meters": 0.762, "time": "13:50", "coefficient": 0.52}, "fourth_tide": {"meters": 2.538, "time": "20:20", "coefficient": 0.52}}, "2020-02-16": {"first_tide": {"meters": 0.85, "time": "02:15", "coefficient": 0.48}, "second_tide": {"meters": 2.527, "time": "08:55", "coefficient": 0.48}, "third_tide": {"meters": 0.977, "time": "14:56", "coefficient": 0.45}, "fourth_tide": {"meters": 2.394, "time": "21:30", "coefficient": 0.45}}, "2020-02-17": {"first_tide": {"meters": 0.998, "time": "03:35", "coefficient": 0.45}, "second_tide": {"meters": 2.375, "time": "10:14", "coefficient": 0.45}, "third_tide": {"meters": 1.094, "time": "16:24", "coefficient": 0.46}, "fourth_tide": {"meters": 2.358, "time": "22:52", "coefficient": 0.46}}, "2020-02-18": {"first_tide": {"meters": 1.005, "time": "05:10", "coefficient": 0.49}, "second_tide": {"meters": 2.346, "time": "11:38", "coefficient": 0.49}, "third_tide": {"meters": 1.06, "time": "17:48", "coefficient": 0.53}}, "2020-02-19": {"first_tide": {"meters": 2.427, "time": "00:07", "coefficient": 0.57}, "second_tide": {"meters": 0.886, "time": "06:26", "coefficient": 0.57}, "third_tide": {"meters": 2.41, "time": "12:49", "coefficient": 0.61}, "fourth_tide": {"meters": 0.933, "time": "18:50", "coefficient": 0.61}}, "2020-02-20": {"first_tide": {"meters": 2.549, "time": "01:08", "coefficient": 0.66}, "second_tide": {"meters": 0.734, "time": "07:21", "coefficient": 0.66}, "third_tide": {"meters": 2.513, "time": "13:43", "coefficient": 0.7}, "fourth_tide": {"meters": 0.797, "time": "19:37", "coefficient": 0.7}}, "2020-02-21": {"first_tide": {"meters": 2.687, "time": "01:56", "coefficient": 0.74}, "second_tide": {"meters": 0.614, "time": "08:05", "coefficient": 0.74}, "third_tide": {"meters": 2.633, "time": "14:26", "coefficient": 0.77}, "fourth_tide": {"meters": 0.691, "time": "20:17", "coefficient": 0.77}}, "2020-02-22": {"first_tide": {"meters": 2.819, "time": "02:37", "coefficient": 0.8}, "second_tide": {"meters": 0.539, "time": "08:43", "coefficient": 0.8}, "third_tide": {"meters": 2.748, "time": "15:03", "coefficient": 0.82}, "fourth_tide": {"meters": 0.623, "time": "20:53", "coefficient": 0.82}}, "2020-02-23": {"first_tide": {"meters": 2.92, "time": "03:14", "coefficient": 0.84}, "second_tide": {"meters": 0.497, "time": "09:18", "coefficient": 0.84}, "third_tide": {"meters": 2.825, "time": "15:36", "coefficient": 0.84}, "fourth_tide": {"meters": 0.577, "time": "21:27", "coefficient": 0.84}}, "2020-02-24": {"first_tide": {"meters": 2.968, "time": "03:47", "coefficient": 0.85}, "second_tide": {"meters": 0.472, "time": "09:50", "coefficient": 0.85}, "third_tide": {"meters": 2.851, "time": "16:08", "coefficient": 0.84}, "fourth_tide": {"meters": 0.545, "time": "21:59", "coefficient": 0.84}}, "2020-02-25": {"first_tide": {"meters": 2.963, "time": "04:19", "coefficient": 0.84}, "second_tide": {"meters": 0.469, "time": "10:21", "coefficient": 0.84}, "third_tide": {"meters": 2.833, "time": "16:38", "coefficient": 0.82}, "fourth_tide": {"meters": 0.542, "time": "22:29", "coefficient": 0.82}}, "2020-02-26": {"first_tide": {"meters": 2.918, "time": "04:50", "coefficient": 0.8}, "second_tide": {"meters": 0.5, "time": "10:50", "coefficient": 0.8}, "third_tide": {"meters": 2.786, "time": "17:06", "coefficient": 0.77}, "fourth_tide": {"meters": 0.579, "time": "22:59", "coefficient": 0.77}}, "2020-02-27": {"first_tide": {"meters": 2.842, "time": "05:19", "coefficient": 0.74}, "second_tide": {"meters": 0.57, "time": "11:19", "coefficient": 0.74}, "third_tide": {"meters": 2.711, "time": "17:35", "coefficient": 0.7}, "fourth_tide": {"meters": 0.655, "time": "23:29", "coefficient": 0.7}}, "2020-02-28": {"first_tide": {"meters": 2.735, "time": "05:49", "coefficient": 0.66}, "second_tide": {"meters": 0.666, "time": "11:48", "coefficient": 0.66}, "third_tide": {"meters": 2.601, "time": "18:04", "coefficient": 0.62}}, "2020-02-29": {"first_tide": {"meters": 0.756, "time": "00:00", "coefficient": 0.57}, "second_tide": {"meters": 2.595, "time": "06:21", "coefficient": 0.57}, "third_tide": {"meters": 0.788, "time": "12:20", "coefficient": 0.53}, "fourth_tide": {"meters": 2.467, "time": "18:37", "coefficient": 0.53}}}