{"port_id":"55","port_code":"morrojable","port_name":"Morro Jable (Fuerteventura)","month":5,"2022-05-01":{"first_tide":{"meters":"2.490","time":"01:11","coefficient":0.85,"high_tide":true},"second_tide":{"meters":"0.358","time":"07:15","coefficient":0.85,"high_tide":false},"third_tide":{"meters":"2.465","time":"13:30","coefficient":0.82,"high_tide":true},"fourth_tide":{"meters":"0.372","time":"19:33","coefficient":0.82,"high_tide":false}},"2022-05-02":{"first_tide":{"meters":"2.400","time":"01:45","coefficient":0.79,"high_tide":true},"second_tide":{"meters":"0.422","time":"07:46","coefficient":0.79,"high_tide":false},"third_tide":{"meters":"2.406","time":"14:02","coefficient":0.75,"high_tide":true},"fourth_tide":{"meters":"0.442","time":"20:07","coefficient":0.75,"high_tide":false}},"2022-05-03":{"first_tide":{"meters":"2.270","time":"02:17","coefficient":0.71,"high_tide":true},"second_tide":{"meters":"0.517","time":"08:16","coefficient":0.71,"high_tide":false},"third_tide":{"meters":"2.303","time":"14:33","coefficient":0.67,"high_tide":true},"fourth_tide":{"meters":"0.548","time":"20:41","coefficient":0.67,"high_tide":false}},"2022-05-04":{"first_tide":{"meters":"2.117","time":"02:49","coefficient":0.62,"high_tide":true},"second_tide":{"meters":"0.634","time":"08:45","coefficient":0.62,"high_tide":false},"third_tide":{"meters":"2.175","time":"15:04","coefficient":0.57,"high_tide":true},"fourth_tide":{"meters":"0.672","time":"21:15","coefficient":0.57,"high_tide":false}},"2022-05-05":{"first_tide":{"meters":"1.958","time":"03:22","coefficient":0.52,"high_tide":true},"second_tide":{"meters":"0.761","time":"09:16","coefficient":0.52,"high_tide":false},"third_tide":{"meters":"2.038","time":"15:38","coefficient":0.47,"high_tide":true},"fourth_tide":{"meters":"0.798","time":"21:54","coefficient":0.47,"high_tide":false}},"2022-05-06":{"first_tide":{"meters":"1.804","time":"04:00","coefficient":0.43,"high_tide":true},"second_tide":{"meters":"0.892","time":"09:51","coefficient":0.43,"high_tide":false},"third_tide":{"meters":"1.907","time":"16:18","coefficient":0.39,"high_tide":true},"fourth_tide":{"meters":"0.911","time":"22:44","coefficient":0.39,"high_tide":false}},"2022-05-07":{"first_tide":{"meters":"1.667","time":"04:51","coefficient":0.35,"high_tide":true},"second_tide":{"meters":"1.014","time":"10:40","coefficient":0.35,"high_tide":false},"third_tide":{"meters":"1.799","time":"17:16","coefficient":0.33,"high_tide":true}},"2022-05-08":{"first_tide":{"meters":"0.982","time":"00:02","coefficient":0.33,"high_tide":false},"second_tide":{"meters":"1.582","time":"06:11","coefficient":0.33,"high_tide":true},"third_tide":{"meters":"1.093","time":"12:03","coefficient":0.34,"high_tide":false},"fourth_tide":{"meters":"1.751","time":"18:41","coefficient":0.34,"high_tide":true}},"2022-05-09":{"first_tide":{"meters":"0.959","time":"01:39","coefficient":0.37,"high_tide":false},"second_tide":{"meters":"1.606","time":"07:48","coefficient":0.37,"high_tide":true},"third_tide":{"meters":"1.063","time":"13:50","coefficient":0.42,"high_tide":false},"fourth_tide":{"meters":"1.807","time":"20:09","coefficient":0.42,"high_tide":true}},"2022-05-10":{"first_tide":{"meters":"0.848","time":"02:50","coefficient":0.47,"high_tide":false},"second_tide":{"meters":"1.733","time":"09:01","coefficient":0.47,"high_tide":true},"third_tide":{"meters":"0.938","time":"15:03","coefficient":0.53,"high_tide":false},"fourth_tide":{"meters":"1.939","time":"21:14","coefficient":0.53,"high_tide":true}},"2022-05-11":{"first_tide":{"meters":"0.699","time":"03:42","coefficient":0.6,"high_tide":false},"second_tide":{"meters":"1.912","time":"09:53","coefficient":0.6,"high_tide":true},"third_tide":{"meters":"0.775","time":"15:56","coefficient":0.66,"high_tide":false},"fourth_tide":{"meters":"2.099","time":"22:05","coefficient":0.66,"high_tide":true}},"2022-05-12":{"first_tide":{"meters":"0.539","time":"04:25","coefficient":0.73,"high_tide":false},"second_tide":{"meters":"2.105","time":"10:36","coefficient":0.73,"high_tide":true},"third_tide":{"meters":"0.607","time":"16:40","coefficient":0.79,"high_tide":false},"fourth_tide":{"meters":"2.256","time":"22:49","coefficient":0.79,"high_tide":true}},"2022-05-13":{"first_tide":{"meters":"0.387","time":"05:05","coefficient":0.85,"high_tide":false},"second_tide":{"meters":"2.284","time":"11:17","coefficient":0.85,"high_tide":true},"third_tide":{"meters":"0.453","time":"17:22","coefficient":0.9,"high_tide":false},"fourth_tide":{"meters":"2.387","time":"23:31","coefficient":0.9,"high_tide":true}},"2022-05-14":{"first_tide":{"meters":"0.261","time":"05:44","coefficient":0.94,"high_tide":false},"second_tide":{"meters":"2.422","time":"11:57","coefficient":0.94,"high_tide":true},"third_tide":{"meters":"0.328","time":"18:02","coefficient":0.98,"high_tide":false}},"2022-05-15":{"first_tide":{"meters":"2.472","time":"00:12","coefficient":1.0,"high_tide":true},"second_tide":{"meters":"0.181","time":"06:23","coefficient":1.0,"high_tide":false},"third_tide":{"meters":"2.508","time":"12:37","coefficient":1.01,"high_tide":true},"fourth_tide":{"meters":"0.247","time":"18:43","coefficient":1.01,"high_tide":false}},"2022-05-16":{"first_tide":{"meters":"2.498","time":"00:54","coefficient":1.0,"high_tide":true},"second_tide":{"meters":"0.165","time":"07:02","coefficient":1.0,"high_tide":false},"third_tide":{"meters":"2.535","time":"13:17","coefficient":0.98,"high_tide":true},"fourth_tide":{"meters":"0.222","time":"19:24","coefficient":0.98,"high_tide":false}},"2022-05-17":{"first_tide":{"meters":"2.460","time":"01:37","coefficient":0.95,"high_tide":true},"second_tide":{"meters":"0.223","time":"07:42","coefficient":0.95,"high_tide":false},"third_tide":{"meters":"2.507","time":"13:59","coefficient":0.91,"high_tide":true},"fourth_tide":{"meters":"0.260","time":"20:07","coefficient":0.91,"high_tide":false}},"2022-05-18":{"first_tide":{"meters":"2.359","time":"02:22","coefficient":0.86,"high_tide":true},"second_tide":{"meters":"0.346","time":"08:23","coefficient":0.86,"high_tide":false},"third_tide":{"meters":"2.431","time":"14:42","coefficient":0.81,"high_tide":true},"fourth_tide":{"meters":"0.357","time":"20:53","coefficient":0.81,"high_tide":false}},"2022-05-19":{"first_tide":{"meters":"2.209","time":"03:10","coefficient":0.75,"high_tide":true},"second_tide":{"meters":"0.517","time":"09:07","coefficient":0.75,"high_tide":false},"third_tide":{"meters":"2.320","time":"15:28","coefficient":0.69,"high_tide":true},"fourth_tide":{"meters":"0.496","time":"21:45","coefficient":0.69,"high_tide":false}},"2022-05-20":{"first_tide":{"meters":"2.031","time":"04:04","coefficient":0.63,"high_tide":true},"second_tide":{"meters":"0.706","time":"09:55","coefficient":0.63,"high_tide":false},"third_tide":{"meters":"2.187","time":"16:20","coefficient":0.58,"high_tide":true},"fourth_tide":{"meters":"0.645","time":"22:46","coefficient":0.58,"high_tide":false}},"2022-05-21":{"first_tide":{"meters":"1.860","time":"05:08","coefficient":0.55,"high_tide":true},"second_tide":{"meters":"0.881","time":"10:53","coefficient":0.55,"high_tide":false},"third_tide":{"meters":"2.058","time":"17:23","coefficient":0.52,"high_tide":true}},"2022-05-22":{"first_tide":{"meters":"0.757","time":"00:04","coefficient":0.51,"high_tide":false},"second_tide":{"meters":"1.748","time":"06:27","coefficient":0.51,"high_tide":true},"third_tide":{"meters":"0.997","time":"12:13","coefficient":0.52,"high_tide":false},"fourth_tide":{"meters":"1.975","time":"18:39","coefficient":0.52,"high_tide":true}},"2022-05-23":{"first_tide":{"meters":"0.784","time":"01:32","coefficient":0.53,"high_tide":false},"second_tide":{"meters":"1.736","time":"07:52","coefficient":0.53,"high_tide":true},"third_tide":{"meters":"1.008","time":"13:44","coefficient":0.56,"high_tide":false},"fourth_tide":{"meters":"1.973","time":"19:59","coefficient":0.56,"high_tide":true}},"2022-05-24":{"first_tide":{"meters":"0.736","time":"02:46","coefficient":0.59,"high_tide":false},"second_tide":{"meters":"1.818","time":"09:04","coefficient":0.59,"high_tide":true},"third_tide":{"meters":"0.927","time":"14:58","coefficient":0.62,"high_tide":false},"fourth_tide":{"meters":"2.043","time":"21:09","coefficient":0.62,"high_tide":true}},"2022-05-25":{"first_tide":{"meters":"0.659","time":"03:43","coefficient":0.65,"high_tide":false},"second_tide":{"meters":"1.950","time":"09:59","coefficient":0.65,"high_tide":true},"third_tide":{"meters":"0.810","time":"15:54","coefficient":0.68,"high_tide":false},"fourth_tide":{"meters":"2.144","time":"22:05","coefficient":0.68,"high_tide":true}},"2022-05-26":{"first_tide":{"meters":"0.585","time":"04:28","coefficient":0.7,"high_tide":false},"second_tide":{"meters":"2.095","time":"10:43","coefficient":0.7,"high_tide":true},"third_tide":{"meters":"0.689","time":"16:41","coefficient":0.73,"high_tide":false},"fourth_tide":{"meters":"2.240","time":"22:51","coefficient":0.73,"high_tide":true}},"2022-05-27":{"first_tide":{"meters":"0.527","time":"05:06","coefficient":0.74,"high_tide":false},"second_tide":{"meters":"2.228","time":"11:22","coefficient":0.74,"high_tide":true},"third_tide":{"meters":"0.586","time":"17:22","coefficient":0.76,"high_tide":false},"fourth_tide":{"meters":"2.306","time":"23:33","coefficient":0.76,"high_tide":true}},"2022-05-28":{"first_tide":{"meters":"0.490","time":"05:41","coefficient":0.76,"high_tide":false},"second_tide":{"meters":"2.331","time":"11:58","coefficient":0.76,"high_tide":true},"third_tide":{"meters":"0.512","time":"18:00","coefficient":0.77,"high_tide":false}},"2022-05-29":{"first_tide":{"meters":"2.328","time":"00:11","coefficient":0.77,"high_tide":true},"second_tide":{"meters":"0.472","time":"06:15","coefficient":0.77,"high_tide":false},"third_tide":{"meters":"2.388","time":"12:32","coefficient":0.76,"high_tide":true},"fourth_tide":{"meters":"0.476","time":"18:37","coefficient":0.76,"high_tide":false}},"2022-05-30":{"first_tide":{"meters":"2.303","time":"00:46","coefficient":0.75,"high_tide":true},"second_tide":{"meters":"0.479","time":"06:47","coefficient":0.75,"high_tide":false},"third_tide":{"meters":"2.396","time":"13:05","coefficient":0.74,"high_tide":true},"fourth_tide":{"meters":"0.479","time":"19:12","coefficient":0.74,"high_tide":false}},"2022-05-31":{"first_tide":{"meters":"2.240","time":"01:21","coefficient":0.72,"high_tide":true},"second_tide":{"meters":"0.510","time":"07:19","coefficient":0.72,"high_tide":false},"third_tide":{"meters":"2.359","time":"13:38","coefficient":0.7,"high_tide":true},"fourth_tide":{"meters":"0.515","time":"19:48","coefficient":0.7,"high_tide":false}}}