{"port_id":"2","port_code":"bilbao","port_name":"Bilbao","month":3,"2022-03-01":{"first_tide":{"meters":"4.139","time":"02:27","coefficient":0.93,"high_tide":true},"second_tide":{"meters":"0.606","time":"08:36","coefficient":0.93,"high_tide":false},"third_tide":{"meters":"4.013","time":"15:00","coefficient":0.97,"high_tide":true},"fourth_tide":{"meters":"0.692","time":"20:54","coefficient":0.97,"high_tide":false}},"2022-03-02":{"first_tide":{"meters":"4.369","time":"03:12","coefficient":0.99,"high_tide":true},"second_tide":{"meters":"0.403","time":"09:20","coefficient":0.99,"high_tide":false},"third_tide":{"meters":"4.162","time":"15:40","coefficient":1.01,"high_tide":true},"fourth_tide":{"meters":"0.509","time":"21:35","coefficient":1.01,"high_tide":false}},"2022-03-03":{"first_tide":{"meters":"4.504","time":"03:52","coefficient":1.01,"high_tide":true},"second_tide":{"meters":"0.310","time":"10:00","coefficient":1.01,"high_tide":false},"third_tide":{"meters":"4.228","time":"16:16","coefficient":1.0,"high_tide":true},"fourth_tide":{"meters":"0.421","time":"22:14","coefficient":1.0,"high_tide":false}},"2022-03-04":{"first_tide":{"meters":"4.523","time":"04:30","coefficient":0.97,"high_tide":true},"second_tide":{"meters":"0.331","time":"10:38","coefficient":0.97,"high_tide":false},"third_tide":{"meters":"4.208","time":"16:50","coefficient":0.94,"high_tide":true},"fourth_tide":{"meters":"0.437","time":"22:51","coefficient":0.94,"high_tide":false}},"2022-03-05":{"first_tide":{"meters":"4.424","time":"05:06","coefficient":0.9,"high_tide":true},"second_tide":{"meters":"0.453","time":"11:14","coefficient":0.9,"high_tide":false},"third_tide":{"meters":"4.108","time":"17:23","coefficient":0.85,"high_tide":true},"fourth_tide":{"meters":"0.554","time":"23:28","coefficient":0.85,"high_tide":false}},"2022-03-06":{"first_tide":{"meters":"4.230","time":"05:41","coefficient":0.79,"high_tide":true},"second_tide":{"meters":"0.653","time":"11:48","coefficient":0.79,"high_tide":false},"third_tide":{"meters":"3.945","time":"17:55","coefficient":0.73,"high_tide":true}},"2022-03-07":{"first_tide":{"meters":"0.757","time":"00:04","coefficient":0.66,"high_tide":false},"second_tide":{"meters":"3.967","time":"06:15","coefficient":0.66,"high_tide":true},"third_tide":{"meters":"0.907","time":"12:23","coefficient":0.59,"high_tide":false},"fourth_tide":{"meters":"3.734","time":"18:28","coefficient":0.59,"high_tide":true}},"2022-03-08":{"first_tide":{"meters":"1.021","time":"00:41","coefficient":0.52,"high_tide":false},"second_tide":{"meters":"3.668","time":"06:51","coefficient":0.52,"high_tide":true},"third_tide":{"meters":"1.192","time":"12:58","coefficient":0.46,"high_tide":false},"fourth_tide":{"meters":"3.495","time":"19:04","coefficient":0.46,"high_tide":true}},"2022-03-09":{"first_tide":{"meters":"1.313","time":"01:21","coefficient":0.39,"high_tide":false},"second_tide":{"meters":"3.362","time":"07:32","coefficient":0.39,"high_tide":true},"third_tide":{"meters":"1.484","time":"13:38","coefficient":0.34,"high_tide":false},"fourth_tide":{"meters":"3.250","time":"19:49","coefficient":0.34,"high_tide":true}},"2022-03-10":{"first_tide":{"meters":"1.598","time":"02:12","coefficient":0.29,"high_tide":false},"second_tide":{"meters":"3.082","time":"08:25","coefficient":0.29,"high_tide":true},"third_tide":{"meters":"1.748","time":"14:31","coefficient":0.27,"high_tide":false},"fourth_tide":{"meters":"3.041","time":"20:54","coefficient":0.27,"high_tide":true}},"2022-03-11":{"first_tide":{"meters":"1.810","time":"03:25","coefficient":0.27,"high_tide":false},"second_tide":{"meters":"2.891","time":"09:49","coefficient":0.27,"high_tide":true},"third_tide":{"meters":"1.922","time":"15:52","coefficient":0.29,"high_tide":false},"fourth_tide":{"meters":"2.960","time":"22:34","coefficient":0.29,"high_tide":true}},"2022-03-12":{"first_tide":{"meters":"1.845","time":"05:07","coefficient":0.33,"high_tide":false},"second_tide":{"meters":"2.895","time":"11:30","coefficient":0.33,"high_tide":true},"third_tide":{"meters":"1.897","time":"17:34","coefficient":0.39,"high_tide":false}},"2022-03-13":{"first_tide":{"meters":"3.074","time":"00:04","coefficient":0.45,"high_tide":true},"second_tide":{"meters":"1.683","time":"06:30","coefficient":0.45,"high_tide":false},"third_tide":{"meters":"3.064","time":"12:44","coefficient":0.51,"high_tide":true},"fourth_tide":{"meters":"1.707","time":"18:46","coefficient":0.51,"high_tide":false}},"2022-03-14":{"first_tide":{"meters":"3.294","time":"01:04","coefficient":0.58,"high_tide":true},"second_tide":{"meters":"1.438","time":"07:23","coefficient":0.58,"high_tide":false},"third_tide":{"meters":"3.300","time":"13:33","coefficient":0.64,"high_tide":true},"fourth_tide":{"meters":"1.455","time":"19:33","coefficient":0.64,"high_tide":false}},"2022-03-15":{"first_tide":{"meters":"3.546","time":"01:47","coefficient":0.71,"high_tide":true},"second_tide":{"meters":"1.174","time":"08:03","coefficient":0.71,"high_tide":false},"third_tide":{"meters":"3.547","time":"14:12","coefficient":0.77,"high_tide":true},"fourth_tide":{"meters":"1.192","time":"20:10","coefficient":0.77,"high_tide":false}},"2022-03-16":{"first_tide":{"meters":"3.795","time":"02:23","coefficient":0.83,"high_tide":true},"second_tide":{"meters":"0.920","time":"08:37","coefficient":0.83,"high_tide":false},"third_tide":{"meters":"3.783","time":"14:45","coefficient":0.88,"high_tide":true},"fourth_tide":{"meters":"0.936","time":"20:44","coefficient":0.88,"high_tide":false}},"2022-03-17":{"first_tide":{"meters":"4.027","time":"02:57","coefficient":0.92,"high_tide":true},"second_tide":{"meters":"0.690","time":"09:09","coefficient":0.92,"high_tide":false},"third_tide":{"meters":"3.992","time":"15:18","coefficient":0.96,"high_tide":true},"fourth_tide":{"meters":"0.710","time":"21:17","coefficient":0.96,"high_tide":false}},"2022-03-18":{"first_tide":{"meters":"4.221","time":"03:30","coefficient":0.99,"high_tide":true},"second_tide":{"meters":"0.509","time":"09:41","coefficient":0.99,"high_tide":false},"third_tide":{"meters":"4.156","time":"15:50","coefficient":1.01,"high_tide":true},"fourth_tide":{"meters":"0.539","time":"21:50","coefficient":1.01,"high_tide":false}},"2022-03-19":{"first_tide":{"meters":"4.360","time":"04:03","coefficient":1.01,"high_tide":true},"second_tide":{"meters":"0.402","time":"10:14","coefficient":1.01,"high_tide":false},"third_tide":{"meters":"4.258","time":"16:23","coefficient":1.0,"high_tide":true},"fourth_tide":{"meters":"0.442","time":"22:23","coefficient":1.0,"high_tide":false}},"2022-03-20":{"first_tide":{"meters":"4.419","time":"04:38","coefficient":0.98,"high_tide":true},"second_tide":{"meters":"0.390","time":"10:48","coefficient":0.98,"high_tide":false},"third_tide":{"meters":"4.281","time":"16:58","coefficient":0.95,"high_tide":true},"fourth_tide":{"meters":"0.439","time":"22:59","coefficient":0.95,"high_tide":false}},"2022-03-21":{"first_tide":{"meters":"4.378","time":"05:15","coefficient":0.91,"high_tide":true},"second_tide":{"meters":"0.483","time":"11:24","coefficient":0.91,"high_tide":false},"third_tide":{"meters":"4.212","time":"17:35","coefficient":0.85,"high_tide":true},"fourth_tide":{"meters":"0.537","time":"23:38","coefficient":0.85,"high_tide":false}},"2022-03-22":{"first_tide":{"meters":"4.225","time":"05:54","coefficient":0.79,"high_tide":true},"second_tide":{"meters":"0.675","time":"12:03","coefficient":0.72,"high_tide":false},"third_tide":{"meters":"4.053","time":"18:15","coefficient":0.72,"high_tide":true}},"2022-03-23":{"first_tide":{"meters":"0.730","time":"00:21","coefficient":0.64,"high_tide":false},"second_tide":{"meters":"3.970","time":"06:38","coefficient":0.64,"high_tide":true},"third_tide":{"meters":"0.954","time":"12:47","coefficient":0.57,"high_tide":false},"fourth_tide":{"meters":"3.825","time":"19:01","coefficient":0.57,"high_tide":true}},"2022-03-24":{"first_tide":{"meters":"0.998","time":"01:12","coefficient":0.5,"high_tide":false},"second_tide":{"meters":"3.652","time":"07:30","coefficient":0.5,"high_tide":true},"third_tide":{"meters":"1.269","time":"13:41","coefficient":0.44,"high_tide":false},"fourth_tide":{"meters":"3.564","time":"20:00","coefficient":0.44,"high_tide":true}},"2022-03-25":{"first_tide":{"meters":"1.277","time":"02:16","coefficient":0.41,"high_tide":false},"second_tide":{"meters":"3.338","time":"08:44","coefficient":0.41,"high_tide":true},"third_tide":{"meters":"1.551","time":"14:51","coefficient":0.41,"high_tide":false},"fourth_tide":{"meters":"3.369","time":"21:25","coefficient":0.41,"high_tide":true}},"2022-03-26":{"first_tide":{"meters":"1.456","time":"03:41","coefficient":0.44,"high_tide":false},"second_tide":{"meters":"3.189","time":"10:29","coefficient":0.44,"high_tide":true},"third_tide":{"meters":"1.660","time":"16:26","coefficient":0.5,"high_tide":false},"fourth_tide":{"meters":"3.380","time":"23:05","coefficient":0.5,"high_tide":true}},"2022-03-27":{"first_tide":{"meters":"1.405","time":"05:20","coefficient":0.56,"high_tide":false},"second_tide":{"meters":"3.296","time":"12:05","coefficient":0.63,"high_tide":true},"third_tide":{"meters":"1.521","time":"17:58","coefficient":0.63,"high_tide":false}},"2022-03-28":{"first_tide":{"meters":"3.585","time":"00:26","coefficient":0.7,"high_tide":true},"second_tide":{"meters":"1.163","time":"06:39","coefficient":0.7,"high_tide":false},"third_tide":{"meters":"3.531","time":"13:12","coefficient":0.77,"high_tide":true},"fourth_tide":{"meters":"1.247","time":"19:04","coefficient":0.77,"high_tide":false}},"2022-03-29":{"first_tide":{"meters":"3.862","time":"01:25","coefficient":0.83,"high_tide":true},"second_tide":{"meters":"0.884","time":"07:35","coefficient":0.83,"high_tide":false},"third_tide":{"meters":"3.779","time":"14:01","coefficient":0.88,"high_tide":true},"fourth_tide":{"meters":"0.964","time":"19:54","coefficient":0.88,"high_tide":false}},"2022-03-30":{"first_tide":{"meters":"4.115","time":"02:13","coefficient":0.92,"high_tide":true},"second_tide":{"meters":"0.656","time":"08:20","coefficient":0.92,"high_tide":false},"third_tide":{"meters":"3.986","time":"14:42","coefficient":0.95,"high_tide":true},"fourth_tide":{"meters":"0.729","time":"20:36","coefficient":0.95,"high_tide":false}},"2022-03-31":{"first_tide":{"meters":"4.305","time":"02:53","coefficient":0.97,"high_tide":true},"second_tide":{"meters":"0.511","time":"08:59","coefficient":0.97,"high_tide":false},"third_tide":{"meters":"4.132","time":"15:17","coefficient":0.98,"high_tide":true},"fourth_tide":{"meters":"0.571","time":"21:14","coefficient":0.98,"high_tide":false}}}