{"port_id":"31","port_code":"lisboa","port_name":"Lisboa","month":7,"2022-07-01":{"first_tide":{"meters":"3.260","time":"04:31","coefficient":0.67,"high_tide":true},"second_tide":{"meters":"0.950","time":"09:48","coefficient":0.67,"high_tide":false},"third_tide":{"meters":"3.510","time":"16:43","coefficient":0.66,"high_tide":true},"fourth_tide":{"meters":"0.910","time":"22:18","coefficient":0.66,"high_tide":false}},"2022-07-02":{"first_tide":{"meters":"3.230","time":"05:05","coefficient":0.64,"high_tide":true},"second_tide":{"meters":"0.990","time":"10:23","coefficient":0.64,"high_tide":false},"third_tide":{"meters":"3.470","time":"17:16","coefficient":0.63,"high_tide":true},"fourth_tide":{"meters":"0.960","time":"22:55","coefficient":0.63,"high_tide":false}},"2022-07-03":{"first_tide":{"meters":"3.190","time":"05:40","coefficient":0.61,"high_tide":true},"second_tide":{"meters":"1.070","time":"11:01","coefficient":0.61,"high_tide":false},"third_tide":{"meters":"3.410","time":"17:50","coefficient":0.59,"high_tide":true},"fourth_tide":{"meters":"1.030","time":"23:34","coefficient":0.59,"high_tide":false}},"2022-07-04":{"first_tide":{"meters":"3.130","time":"06:15","coefficient":0.58,"high_tide":true},"second_tide":{"meters":"1.160","time":"11:41","coefficient":0.58,"high_tide":false},"third_tide":{"meters":"3.350","time":"18:25","coefficient":0.56,"high_tide":true}},"2022-07-05":{"first_tide":{"meters":"1.120","time":"00:17","coefficient":0.55,"high_tide":false},"second_tide":{"meters":"3.080","time":"06:54","coefficient":0.55,"high_tide":true},"third_tide":{"meters":"1.260","time":"12:27","coefficient":0.54,"high_tide":false},"fourth_tide":{"meters":"3.270","time":"19:06","coefficient":0.54,"high_tide":true}},"2022-07-06":{"first_tide":{"meters":"1.210","time":"01:07","coefficient":0.53,"high_tide":false},"second_tide":{"meters":"3.030","time":"07:40","coefficient":0.53,"high_tide":true},"third_tide":{"meters":"1.360","time":"13:22","coefficient":0.53,"high_tide":false},"fourth_tide":{"meters":"3.200","time":"19:55","coefficient":0.53,"high_tide":true}},"2022-07-07":{"first_tide":{"meters":"1.280","time":"02:06","coefficient":0.54,"high_tide":false},"second_tide":{"meters":"3.010","time":"08:36","coefficient":0.54,"high_tide":true},"third_tide":{"meters":"1.410","time":"14:28","coefficient":0.55,"high_tide":false},"fourth_tide":{"meters":"3.140","time":"20:56","coefficient":0.55,"high_tide":true}},"2022-07-08":{"first_tide":{"meters":"1.290","time":"03:12","coefficient":0.57,"high_tide":false},"second_tide":{"meters":"3.040","time":"09:43","coefficient":0.57,"high_tide":true},"third_tide":{"meters":"1.380","time":"15:40","coefficient":0.59,"high_tide":false},"fourth_tide":{"meters":"3.140","time":"22:08","coefficient":0.59,"high_tide":true}},"2022-07-09":{"first_tide":{"meters":"1.230","time":"04:21","coefficient":0.62,"high_tide":false},"second_tide":{"meters":"3.140","time":"10:54","coefficient":0.62,"high_tide":true},"third_tide":{"meters":"1.250","time":"16:51","coefficient":0.66,"high_tide":false},"fourth_tide":{"meters":"3.210","time":"23:22","coefficient":0.66,"high_tide":true}},"2022-07-10":{"first_tide":{"meters":"1.100","time":"05:24","coefficient":0.7,"high_tide":false},"second_tide":{"meters":"3.310","time":"12:01","coefficient":0.74,"high_tide":true},"third_tide":{"meters":"1.060","time":"17:55","coefficient":0.74,"high_tide":false}},"2022-07-11":{"first_tide":{"meters":"3.340","time":"00:30","coefficient":0.78,"high_tide":true},"second_tide":{"meters":"0.940","time":"06:22","coefficient":0.78,"high_tide":false},"third_tide":{"meters":"3.510","time":"13:01","coefficient":0.82,"high_tide":true},"fourth_tide":{"meters":"0.830","time":"18:53","coefficient":0.82,"high_tide":false}},"2022-07-12":{"first_tide":{"meters":"3.480","time":"01:32","coefficient":0.86,"high_tide":true},"second_tide":{"meters":"0.780","time":"07:16","coefficient":0.86,"high_tide":false},"third_tide":{"meters":"3.710","time":"13:57","coefficient":0.89,"high_tide":true},"fourth_tide":{"meters":"0.630","time":"19:46","coefficient":0.89,"high_tide":false}},"2022-07-13":{"first_tide":{"meters":"3.620","time":"02:28","coefficient":0.92,"high_tide":true},"second_tide":{"meters":"0.650","time":"08:06","coefficient":0.92,"high_tide":false},"third_tide":{"meters":"3.890","time":"14:49","coefficient":0.93,"high_tide":true},"fourth_tide":{"meters":"0.480","time":"20:37","coefficient":0.93,"high_tide":false}},"2022-07-14":{"first_tide":{"meters":"3.720","time":"03:20","coefficient":0.94,"high_tide":true},"second_tide":{"meters":"0.580","time":"08:54","coefficient":0.94,"high_tide":false},"third_tide":{"meters":"4.020","time":"15:39","coefficient":0.94,"high_tide":true},"fourth_tide":{"meters":"0.400","time":"21:26","coefficient":0.94,"high_tide":false}},"2022-07-15":{"first_tide":{"meters":"3.770","time":"04:09","coefficient":0.93,"high_tide":true},"second_tide":{"meters":"0.570","time":"09:41","coefficient":0.93,"high_tide":false},"third_tide":{"meters":"4.080","time":"16:26","coefficient":0.91,"high_tide":true},"fourth_tide":{"meters":"0.420","time":"22:15","coefficient":0.91,"high_tide":false}},"2022-07-16":{"first_tide":{"meters":"3.760","time":"04:56","coefficient":0.89,"high_tide":true},"second_tide":{"meters":"0.640","time":"10:27","coefficient":0.89,"high_tide":false},"third_tide":{"meters":"4.060","time":"17:12","coefficient":0.85,"high_tide":true},"fourth_tide":{"meters":"0.530","time":"23:02","coefficient":0.85,"high_tide":false}},"2022-07-17":{"first_tide":{"meters":"3.670","time":"05:41","coefficient":0.81,"high_tide":true},"second_tide":{"meters":"0.760","time":"11:13","coefficient":0.81,"high_tide":false},"third_tide":{"meters":"3.960","time":"17:58","coefficient":0.77,"high_tide":true},"fourth_tide":{"meters":"0.710","time":"23:51","coefficient":0.77,"high_tide":false}},"2022-07-18":{"first_tide":{"meters":"3.540","time":"06:27","coefficient":0.72,"high_tide":true},"second_tide":{"meters":"0.940","time":"12:01","coefficient":0.67,"high_tide":false},"third_tide":{"meters":"3.780","time":"18:45","coefficient":0.67,"high_tide":true}},"2022-07-19":{"first_tide":{"meters":"0.940","time":"00:41","coefficient":0.62,"high_tide":false},"second_tide":{"meters":"3.370","time":"07:14","coefficient":0.62,"high_tide":true},"third_tide":{"meters":"1.150","time":"12:53","coefficient":0.57,"high_tide":false},"fourth_tide":{"meters":"3.550","time":"19:34","coefficient":0.57,"high_tide":true}},"2022-07-20":{"first_tide":{"meters":"1.180","time":"01:35","coefficient":0.53,"high_tide":false},"second_tide":{"meters":"3.200","time":"08:06","coefficient":0.53,"high_tide":true},"third_tide":{"meters":"1.350","time":"13:52","coefficient":0.49,"high_tide":false},"fourth_tide":{"meters":"3.310","time":"20:30","coefficient":0.49,"high_tide":true}},"2022-07-21":{"first_tide":{"meters":"1.380","time":"02:35","coefficient":0.46,"high_tide":false},"second_tide":{"meters":"3.060","time":"09:05","coefficient":0.46,"high_tide":true},"third_tide":{"meters":"1.500","time":"15:01","coefficient":0.44,"high_tide":false},"fourth_tide":{"meters":"3.110","time":"21:34","coefficient":0.44,"high_tide":true}},"2022-07-22":{"first_tide":{"meters":"1.510","time":"03:41","coefficient":0.44,"high_tide":false},"second_tide":{"meters":"3.000","time":"10:14","coefficient":0.44,"high_tide":true},"third_tide":{"meters":"1.560","time":"16:15","coefficient":0.44,"high_tide":false},"fourth_tide":{"meters":"3.010","time":"22:47","coefficient":0.44,"high_tide":true}},"2022-07-23":{"first_tide":{"meters":"1.540","time":"04:46","coefficient":0.45,"high_tide":false},"second_tide":{"meters":"3.040","time":"11:25","coefficient":0.45,"high_tide":true},"third_tide":{"meters":"1.520","time":"17:25","coefficient":0.47,"high_tide":false},"fourth_tide":{"meters":"3.000","time":"23:55","coefficient":0.47,"high_tide":true}},"2022-07-24":{"first_tide":{"meters":"1.480","time":"05:43","coefficient":0.5,"high_tide":false},"second_tide":{"meters":"3.140","time":"12:26","coefficient":0.53,"high_tide":true},"third_tide":{"meters":"1.420","time":"18:22","coefficient":0.53,"high_tide":false}},"2022-07-25":{"first_tide":{"meters":"3.050","time":"00:53","coefficient":0.56,"high_tide":true},"second_tide":{"meters":"1.380","time":"06:32","coefficient":0.56,"high_tide":false},"third_tide":{"meters":"3.260","time":"13:17","coefficient":0.59,"high_tide":true},"fourth_tide":{"meters":"1.280","time":"19:08","coefficient":0.59,"high_tide":false}},"2022-07-26":{"first_tide":{"meters":"3.130","time":"01:42","coefficient":0.62,"high_tide":true},"second_tide":{"meters":"1.250","time":"07:13","coefficient":0.62,"high_tide":false},"third_tide":{"meters":"3.380","time":"14:01","coefficient":0.65,"high_tide":true},"fourth_tide":{"meters":"1.140","time":"19:47","coefficient":0.65,"high_tide":false}},"2022-07-27":{"first_tide":{"meters":"3.220","time":"02:24","coefficient":0.67,"high_tide":true},"second_tide":{"meters":"1.130","time":"07:50","coefficient":0.67,"high_tide":false},"third_tide":{"meters":"3.490","time":"14:41","coefficient":0.7,"high_tide":true},"fourth_tide":{"meters":"1.010","time":"20:22","coefficient":0.7,"high_tide":false}},"2022-07-28":{"first_tide":{"meters":"3.300","time":"03:03","coefficient":0.72,"high_tide":true},"second_tide":{"meters":"1.010","time":"08:25","coefficient":0.72,"high_tide":false},"third_tide":{"meters":"3.580","time":"15:17","coefficient":0.73,"high_tide":true},"fourth_tide":{"meters":"0.910","time":"20:55","coefficient":0.73,"high_tide":false}},"2022-07-29":{"first_tide":{"meters":"3.370","time":"03:39","coefficient":0.75,"high_tide":true},"second_tide":{"meters":"0.930","time":"09:00","coefficient":0.75,"high_tide":false},"third_tide":{"meters":"3.640","time":"15:52","coefficient":0.76,"high_tide":true},"fourth_tide":{"meters":"0.830","time":"21:28","coefficient":0.76,"high_tide":false}},"2022-07-30":{"first_tide":{"meters":"3.420","time":"04:12","coefficient":0.76,"high_tide":true},"second_tide":{"meters":"0.870","time":"09:33","coefficient":0.76,"high_tide":false},"third_tide":{"meters":"3.680","time":"16:24","coefficient":0.76,"high_tide":true},"fourth_tide":{"meters":"0.790","time":"22:01","coefficient":0.76,"high_tide":false}},"2022-07-31":{"first_tide":{"meters":"3.440","time":"04:44","coefficient":0.76,"high_tide":true},"second_tide":{"meters":"0.850","time":"10:07","coefficient":0.76,"high_tide":false},"third_tide":{"meters":"3.680","time":"16:55","coefficient":0.75,"high_tide":true},"fourth_tide":{"meters":"0.800","time":"22:34","coefficient":0.75,"high_tide":false}}}